XiYun/__init__.py
XiYun/a.py
XiYun-0.0.1.dist-info/LICENSE.txt
XiYun-0.0.1.dist-info/METADATA
XiYun-0.0.1.dist-info/WHEEL
XiYun-0.0.1.dist-info/top_level.txt
XiYun-0.0.1.dist-info/RECORD
