Metadata-Version: 2.1
Name: XiYun
Version: 0.0.1
Summary: GUI项目
Home-page: https://github.com/BigDataFounder/XiYun
Author: 凉笙
Author-email: author@example.com
Requires-Python: >=3.9
License-File: LICENSE.txt
